leroque/__init__.py
leroque/rr.py
leroque/utils.py
leroque-1.1.6.dist-info/LICENSE
leroque-1.1.6.dist-info/METADATA
leroque-1.1.6.dist-info/WHEEL
leroque-1.1.6.dist-info/top_level.txt
leroque-1.1.6.dist-info/RECORD
