Metadata-Version: 2.1
Name: leroque
Version: 1.1.6
Summary: An RR wrapper
Home-page: https://github.com/bagd1k/leroque
Author: bagd1k
Author-email: bogdan@yobangelion.ru
License: UNKNOWN
Project-URL: Bug Tracker, https://github.com/bagd1k/leroque/issues
Platform: UNKNOWN
Classifier: Programming Language :: Python :: 3
Classifier: License :: OSI Approved :: MIT License
Classifier: Operating System :: OS Independent
Requires-Python: >=3.6
License-File: LICENSE
Requires-Dist: requests
Requires-Dist: beautifulsoup4
